{
    "Город": "Население Казани",
    "Количество людей": "1 257 391",
    "Место в рейтинге": "место занимает Россия в рейтинге стран по численности населения",
    "Численность населения по возрастным группам": {
        "Дети до 6 лет": "125 582",
        "Подростки от 7 до 17": "148 529",
        "Молодежь от 18 до 29": "150 730",
        "Взрослые от 30 до 59": "540 835",
        "Пожилые старше 60": "274 111",
        "Долгожители старше 80": "17 603",
        "Татары": "668 932",
        "Русские": "499 184",
        "Чуваши": "38 979",
        "Возраст": "N/A",
        "0 – 4": "N/A",
        "5 – 9": "N/A",
        "10 - 14": "N/A",
        "15 - 19": "N/A",
        "20 - 24": "N/A",
        "25 - 29": "N/A",
        "30 - 34": "N/A",
        "35 - 39": "N/A",
        "40 - 44": "N/A",
        "45 - 49": "N/A",
        "50 - 54": "N/A",
        "55 - 59": "N/A",
        "60 - 64": "N/A",
        "65 - 69": "N/A",
        "70 - 74": "N/A",
        "75 - 79": "N/A",
        "80+": "N/A",
        "Высшее": "269 082",
        "Неполное высшее": "27 663",
        "Среднее профессиональное": "441 344",
        "11 классов": "230 103",
        "9 классов": "113 165",
        "5 классов": "110 650",
        "Без образования": "6 287",
        "Неграмотные": "2 515",
        "Занятого населения": "749 405",
        "Безработных": "72 929",
        "Пенсионеров": "364 643",
        "Всего инвалидов": "100 214",
        "Инвалидов 1-й группы": "11 819",
        "Инвалидов 2-й группы": "42 877",
        "Инвалидов 3-й группы": "39 482",
        "Детей-инвалидов": "6 035"
    },
    "Гендерный состав населения": {
        "Дети до 6 лет": {
            "male": "N/A",
            "female": "N/A"
        },
        "Подростки от 7 до 17": {
            "male": "N/A",
            "female": "N/A"
        },
        "Молодежь от 18 до 29": {
            "male": "N/A",
            "female": "N/A"
        },
        "Взрослые от 30 до 59": {
            "male": "N/A",
            "female": "N/A"
        },
        "Пожилые старше 60": {
            "male": "N/A",
            "female": "N/A"
        },
        "Долгожители старше 80": {
            "male": "N/A",
            "female": "N/A"
        },
        "Татары": {
            "male": "N/A",
            "female": "N/A"
        },
        "Русские": {
            "male": "N/A",
            "female": "N/A"
        },
        "Чуваши": {
            "male": "N/A",
            "female": "N/A"
        },
        "Возраст": {
            "male": "N/A",
            "female": "N/A"
        },
        "0 – 4": {
            "male": "N/A",
            "female": "N/A"
        },
        "5 – 9": {
            "male": "N/A",
            "female": "N/A"
        },
        "10 - 14": {
            "male": "N/A",
            "female": "N/A"
        },
        "15 - 19": {
            "male": "N/A",
            "female": "N/A"
        },
        "20 - 24": {
            "male": "N/A",
            "female": "N/A"
        },
        "25 - 29": {
            "male": "N/A",
            "female": "N/A"
        },
        "30 - 34": {
            "male": "N/A",
            "female": "N/A"
        },
        "35 - 39": {
            "male": "N/A",
            "female": "N/A"
        },
        "40 - 44": {
            "male": "N/A",
            "female": "N/A"
        },
        "45 - 49": {
            "male": "N/A",
            "female": "N/A"
        },
        "50 - 54": {
            "male": "N/A",
            "female": "N/A"
        },
        "55 - 59": {
            "male": "N/A",
            "female": "N/A"
        },
        "60 - 64": {
            "male": "N/A",
            "female": "N/A"
        },
        "65 - 69": {
            "male": "N/A",
            "female": "N/A"
        },
        "70 - 74": {
            "male": "N/A",
            "female": "N/A"
        },
        "75 - 79": {
            "male": "N/A",
            "female": "N/A"
        },
        "80+": {
            "male": "N/A",
            "female": "N/A"
        },
        "Высшее": {
            "male": "N/A",
            "female": "N/A"
        },
        "Неполное высшее": {
            "male": "N/A",
            "female": "N/A"
        },
        "Среднее профессиональное": {
            "male": "N/A",
            "female": "N/A"
        },
        "11 классов": {
            "male": "N/A",
            "female": "N/A"
        },
        "9 классов": {
            "male": "N/A",
            "female": "N/A"
        },
        "5 классов": {
            "male": "N/A",
            "female": "N/A"
        },
        "Без образования": {
            "male": "N/A",
            "female": "N/A"
        },
        "Неграмотные": {
            "male": "N/A",
            "female": "N/A"
        },
        "Занятого населения": {
            "male": "N/A",
            "female": "N/A"
        },
        "Безработных": {
            "male": "N/A",
            "female": "N/A"
        },
        "Пенсионеров": {
            "male": "N/A",
            "female": "N/A"
        },
        "Всего инвалидов": {
            "male": "N/A",
            "female": "N/A"
        },
        "Инвалидов 1-й группы": {
            "male": "N/A",
            "female": "N/A"
        },
        "Инвалидов 2-й группы": {
            "male": "N/A",
            "female": "N/A"
        },
        "Инвалидов 3-й группы": {
            "male": "N/A",
            "female": "N/A"
        },
        "Детей-инвалидов": {
            "male": "N/A",
            "female": "N/A"
        }
    },
    "Занятость населения, безработица и пенсионеры": {
        "Дети до 6 лет": "125 582",
        "Подростки от 7 до 17": "148 529",
        "Молодежь от 18 до 29": "150 730",
        "Взрослые от 30 до 59": "540 835",
        "Пожилые старше 60": "274 111",
        "Долгожители старше 80": "17 603",
        "Татары": "668 932",
        "Русские": "499 184",
        "Чуваши": "38 979",
        "Возраст": "N/A",
        "0 – 4": "N/A",
        "5 – 9": "N/A",
        "10 - 14": "N/A",
        "15 - 19": "N/A",
        "20 - 24": "N/A",
        "25 - 29": "N/A",
        "30 - 34": "N/A",
        "35 - 39": "N/A",
        "40 - 44": "N/A",
        "45 - 49": "N/A",
        "50 - 54": "N/A",
        "55 - 59": "N/A",
        "60 - 64": "N/A",
        "65 - 69": "N/A",
        "70 - 74": "N/A",
        "75 - 79": "N/A",
        "80+": "N/A",
        "Высшее": "269 082",
        "Неполное высшее": "27 663",
        "Среднее профессиональное": "441 344",
        "11 классов": "230 103",
        "9 классов": "113 165",
        "5 классов": "110 650",
        "Без образования": "6 287",
        "Неграмотные": "2 515",
        "Занятого населения": "749 405",
        "Безработных": "72 929",
        "Пенсионеров": "364 643",
        "Всего инвалидов": "100 214",
        "Инвалидов 1-й группы": "11 819",
        "Инвалидов 2-й группы": "42 877",
        "Инвалидов 3-й группы": "39 482",
        "Детей-инвалидов": "6 035"
    },
    "Инвалидность": {
        "Дети до 6 лет": "125 582",
        "Подростки от 7 до 17": "148 529",
        "Молодежь от 18 до 29": "150 730",
        "Взрослые от 30 до 59": "540 835",
        "Пожилые старше 60": "274 111",
        "Долгожители старше 80": "17 603",
        "Татары": "668 932",
        "Русские": "499 184",
        "Чуваши": "38 979",
        "Возраст": "N/A",
        "0 – 4": "N/A",
        "5 – 9": "N/A",
        "10 - 14": "N/A",
        "15 - 19": "N/A",
        "20 - 24": "N/A",
        "25 - 29": "N/A",
        "30 - 34": "N/A",
        "35 - 39": "N/A",
        "40 - 44": "N/A",
        "45 - 49": "N/A",
        "50 - 54": "N/A",
        "55 - 59": "N/A",
        "60 - 64": "N/A",
        "65 - 69": "N/A",
        "70 - 74": "N/A",
        "75 - 79": "N/A",
        "80+": "N/A",
        "Высшее": "269 082",
        "Неполное высшее": "27 663",
        "Среднее профессиональное": "441 344",
        "11 классов": "230 103",
        "9 классов": "113 165",
        "5 классов": "110 650",
        "Без образования": "6 287",
        "Неграмотные": "2 515",
        "Занятого населения": "749 405",
        "Безработных": "72 929",
        "Пенсионеров": "364 643",
        "Всего инвалидов": "100 214",
        "Инвалидов 1-й группы": "11 819",
        "Инвалидов 2-й группы": "42 877",
        "Инвалидов 3-й группы": "39 482",
        "Детей-инвалидов": "6 035"
    }
}